uart/__init__.py
uart/__main__.py
uart/bus.py
uart/documentation.py
uart/editor.py
uart/exceptions.py
uart/field.py
uart/header.py
uart/module.py
uart/register.py
uart/utils.py
uart/vhdl.py
uart-0.6.4.dist-info/METADATA
uart-0.6.4.dist-info/RECORD
uart-0.6.4.dist-info/WHEEL
uart-0.6.4.dist-info/entry_points.txt
uart-0.6.4.dist-info/top_level.txt
